wagtailautocomplete/__init__.py
wagtailautocomplete/edit_handlers.py
wagtailautocomplete/views.py
wagtailautocomplete/widgets.py
wagtailautocomplete/static/wagtailautocomplete/controller.js
wagtailautocomplete/static/wagtailautocomplete/dist.css
wagtailautocomplete/static/wagtailautocomplete/dist.js
wagtailautocomplete/static/wagtailautocomplete/dist.js.LICENSE.txt
wagtailautocomplete/templates/wagtailautocomplete/autocomplete.html
wagtailautocomplete/tests/__init__.py
wagtailautocomplete/tests/settings.py
wagtailautocomplete/tests/test_autocomplete_views.py
wagtailautocomplete/tests/test_edit_handlers.py
wagtailautocomplete/tests/testapp/__init__.py
wagtailautocomplete/tests/testapp/models.py
wagtailautocomplete/tests/testapp/urls.py
wagtailautocomplete/tests/testapp/migrations/0001_initial.py
wagtailautocomplete/tests/testapp/migrations/__init__.py
wagtailautocomplete/urls/__init__.py
wagtailautocomplete/urls/admin.py
wagtailautocomplete/urls/public.py
wagtail_autocomplete-0.12.0.dist-info/LICENSE
wagtail_autocomplete-0.12.0.dist-info/METADATA
wagtail_autocomplete-0.12.0.dist-info/WHEEL
wagtail_autocomplete-0.12.0.dist-info/top_level.txt
wagtail_autocomplete-0.12.0.dist-info/RECORD
