Metadata-Version: 2.2
Name: wagtail-autocomplete
Version: 0.12.0
Summary: An Autocomplete edit handler for Pages, Snippets, and more.
Home-page: https://github.com/wagtail/wagtail-autocomplete
Author: Emily Horsman and Harris Lapiroff
Author-email: me@emilyhorsman.com
License: BSD-3-Clause
Classifier: Development Status :: 4 - Beta
Classifier: Environment :: Web Environment
Classifier: Intended Audience :: Developers
Classifier: License :: OSI Approved :: BSD License
Classifier: Operating System :: OS Independent
Classifier: Programming Language :: Python
Classifier: Programming Language :: Python :: 3.8
Classifier: Programming Language :: Python :: 3.9
Classifier: Programming Language :: Python :: 3.10
Classifier: Programming Language :: Python :: 3.11
Classifier: Framework :: Django
Classifier: Framework :: Django :: 3
Classifier: Framework :: Django :: 3.2
Classifier: Framework :: Django :: 4
Classifier: Framework :: Django :: 4.1
Classifier: Framework :: Django :: 4.2
Classifier: Framework :: Wagtail
Classifier: Framework :: Wagtail :: 4
Classifier: Framework :: Wagtail :: 5
Classifier: Topic :: Internet :: WWW/HTTP
Classifier: Topic :: Internet :: WWW/HTTP :: Dynamic Content
License-File: LICENSE
Requires-Dist: wagtail>=4.1
Provides-Extra: docs
Requires-Dist: Sphinx>=1.7; extra == "docs"
Requires-Dist: sphinx_rtd_theme>=0.4.0; extra == "docs"
Provides-Extra: test
Requires-Dist: tox; extra == "test"
Requires-Dist: pytest>=3.5; extra == "test"
Requires-Dist: pytest-django>=3.2; extra == "test"
Requires-Dist: beautifulsoup4>=4.8; extra == "test"
Requires-Dist: html5lib>=0.999999999; extra == "test"
Requires-Dist: pytest-pythonpath>=0.7.2; extra == "test"
Dynamic: author
Dynamic: author-email
Dynamic: classifier
Dynamic: description
Dynamic: home-page
Dynamic: license
Dynamic: provides-extra
Dynamic: requires-dist
Dynamic: summary
